rucio_noauth/__init__.py
rucio_noauth/api.py
rucio_noauth/cli.py
rucio_noauth/util.py
rucio_noauth-0.0.1.dist-info/METADATA
rucio_noauth-0.0.1.dist-info/WHEEL
rucio_noauth-0.0.1.dist-info/entry_points.txt
rucio_noauth-0.0.1.dist-info/top_level.txt
rucio_noauth-0.0.1.dist-info/RECORD
