Metadata-Version: 2.1
Name: rucio-noauth
Version: 0.0.1
Summary: CLI client for Rucio server without authentication
Author-email: Your Name <your.email@example.com>
License: MIT
Classifier: Programming Language :: Python :: 3
Classifier: License :: OSI Approved :: MIT License
Classifier: Operating System :: OS Independent
Requires-Python: >=3.9
Requires-Dist: click>=8.1.7
Requires-Dist: requests>=2.32.3
Requires-Dist: rich>=13.7.1
